{"id":124722,"date":"2020-11-11T18:48:59.000Z","description":null,"for":604,"against":33,"abstention":49,"plenary":null,"name":"Emmanuel Maurel - Vote unique","ref":"A9-0175/2020","green_remark":null,"created_by":null,"updated_by":null,"title":"Introducing exceptional trade measures for countries and territories participating in or linked to the European Union's Stabilisation and Association process","url":"https://oeil.secure.europarl.europa.eu/oeil//popups/ficheprocedure.do?reference=2020/0051(COD)&amp;l=en"}