{"id":130656,"date":"2021-04-27T20:24:58.000Z","description":null,"for":635,"against":24,"abstention":39,"plenary":null,"name":"Décharge 2019 : Institut européen d'innovation et de technologie - 2019 discharge: European Institute of Innovation and Technology - Entlastung 2019: Europäisches Innovations- und Technologieinstitut -  - Ryszard Czarnecki - Propositions de décision\n","ref":"A9-0076/2021","green_remark":null,"created_by":null,"updated_by":null,"title":"2019 discharge: European Institute of Innovation and Technology (EIT)","url":"https://oeil.secure.europarl.europa.eu/oeil//popups/ficheprocedure.do?reference=2020/2179(DEC)&l=en"}