{"id":137372,"date":"2021-11-24T13:50:29.000Z","description":null,"for":60,"against":521,"abstention":108,"plenary":null,"name":"Mobilisation du Fonds européen d’ajustement à la mondialisation - EGF/2021/001 ES/País Vasco metal - Espagne - Mobilisation of the European Globalisation Adjustment Fund: application EGF/2021/001 ES/País Vasco metal – Spain - Inanspruchnahme des Europäischen Fonds für die Anpassung an die Globalisierung – EGF/2021/001 ES/País Vasco metal – Spanien -  - Eider Gardiazabal Rubial - § 9 - Am 1","ref":"A9-0319/2021","green_remark":null,"created_by":null,"updated_by":null,"title":"Mobilisation of the European Globalisation Adjustment Fund: redundancies in metal products manufacturing in Spain","url":"https://oeil.secure.europarl.europa.eu/oeil//popups/ficheprocedure.do?reference=2021/0316(BUD)&amp;l=en"}