{"id":138178,"date":"2021-12-16T14:32:12.000Z","description":null,"for":548,"against":69,"abstention":54,"plenary":null,"name":"Situation à la frontière ukrainienne et dans les territoires de l'Ukraine occupés par la Russie - Situation at the Ukrainian border and in Russian-occupied territories of Ukraine - Die Lage an der ukrainischen Grenze und in den von Russland besetzten Gebieten in der Ukraine - RC- - Proposition de résolution (ensemble du texte) ","ref":"B9-0594/2021","green_remark":null,"created_by":null,"updated_by":null,"title":"Situation at the Ukrainian border and in Russian-occupied territories of Ukraine","url":"https://oeil.secure.europarl.europa.eu/oeil//popups/ficheprocedure.do?reference=2021/3010(RSP)&amp;l=en"}