{"id":160195,"date":"2023-11-21T11:36:15.000Z","description":null,"for":376,"against":139,"abstention":116,"plenary":null,"name":"Christian Ehler - Proposition de la Commission","ref":"A9-0343/2023","green_remark":null,"created_by":null,"updated_by":null,"title":"Framework of measures for strengthening Europe’s net-zero technology products manufacturing ecosystem (Net Zero Industry Act)","url":"https://oeil.secure.europarl.europa.eu/oeil//popups/ficheprocedure.do?reference=2023/0081(COD)&amp;l=en"}