{"id":162157,"date":"2023-12-12T11:11:55.000Z","description":null,"for":601,"against":1,"abstention":6,"plenary":null,"name":"Autorisation octroyée à la France de négocier un accord bilatéral avec l’Algérie sur des questions liées à la coopération judiciaire en matière civile et commerciale - Authorisation empowering France to negotiate a bilateral agreement with Algeria concerning judicial cooperation in civil and commercial matters - Ermächtigung Frankreichs zur Aushandlung eines bilateralen Abkommens mit Algerien über die justizielle Zusammenarbeit in Zivil- und Handelssachen -  - Ilana Cicurel - Proposition de la Commission et amendements","ref":"A9-0356/2023","green_remark":null,"created_by":null,"updated_by":null,"title":"Authorisation addressed to France to negotiate a bilateral agreement with Algeria on matters related to judicial cooperation in civil and commercial matters","url":"https://oeil.secure.europarl.europa.eu/oeil//popups/ficheprocedure.do?reference=2023/0028(COD)&amp;l=en"}