{"id":168984,"date":"2024-04-25T10:40:48.000Z","description":null,"for":301,"against":216,"abstention":23,"plenary":null,"name":"Daniel Freund - Proposition de décision (ensemble du texte)","ref":"A9-0181/2024","green_remark":null,"created_by":null,"updated_by":null,"title":"European Parliament/Council/European Commission/Court of Justice/European Central Bank/European Court of Auditors/European Economic and Social Committee/European Committee of the Regions Agreement: establishing an Interinstitutional Body for Ethical Standards for Members of Institutions and advisory bodies","url":"https://oeil.secure.europarl.europa.eu/oeil//popups/ficheprocedure.do?reference=2024/2008(ACI)&amp;l=en"}